objdict_bf/__init__.py
objdict_bf/objdict.py
tests/__init__.py
objdict_bf-0.1.24.dist-info/LICENSE
objdict_bf-0.1.24.dist-info/METADATA
objdict_bf-0.1.24.dist-info/WHEEL
objdict_bf-0.1.24.dist-info/top_level.txt
objdict_bf-0.1.24.dist-info/RECORD
