Metadata-Version: 2.1
Name: objdict-bf
Version: 0.1.24
Summary: A custom wrapper object around dict that allows attribute-style access to dictionary items and support for serialization of nested data.
Home-page: https://github.com/B4PT0R/objdict
Author: Baptiste Ferrand
Author-email: bferrand.maths@gmail.com
Classifier: Programming Language :: Python :: 3
Classifier: License :: OSI Approved :: MIT License
Classifier: Operating System :: OS Independent
Requires-Python: >=3.6
License-File: LICENSE
Requires-Dist: jsonpickle
Requires-Dist: toml
Requires-Dist: pyyaml
